exllamav2/__init__.py
exllamav2/architecture.py
exllamav2/attn.py
exllamav2/attn_params.py
exllamav2/cache.py
exllamav2/compat.py
exllamav2/config.py
exllamav2/conv.py
exllamav2/device.py
exllamav2/embedding.py
exllamav2/ext.py
exllamav2/headnorm.py
exllamav2/layernorm.py
exllamav2/linear.py
exllamav2/lora.py
exllamav2/mlp.py
exllamav2/model.py
exllamav2/model_init.py
exllamav2/module.py
exllamav2/moe_mlp.py
exllamav2/mrope.py
exllamav2/parallel_decoder.py
exllamav2/pos_embedding.py
exllamav2/py.typed
exllamav2/rmsnorm.py
exllamav2/rope.py
exllamav2/stloader.py
exllamav2/tensor_p.py
exllamav2/util.py
exllamav2/version.py
exllamav2/conversion/adaptivegptq.py
exllamav2/conversion/bot_status.py
exllamav2/conversion/compile.py
exllamav2/conversion/convert_exl2.py
exllamav2/conversion/measure.py
exllamav2/conversion/optimize.py
exllamav2/conversion/qparams.py
exllamav2/conversion/quantize.py
exllamav2/conversion/tokenize.py
exllamav2/conversion/standard_cal_data/c4.utf8
exllamav2/conversion/standard_cal_data/code.utf8
exllamav2/conversion/standard_cal_data/multilingual.utf8
exllamav2/conversion/standard_cal_data/technical.utf8
exllamav2/conversion/standard_cal_data/tiny.utf8
exllamav2/conversion/standard_cal_data/wiki.utf8
exllamav2/exllamav2_ext/config.h
exllamav2/exllamav2_ext/ext_bindings.cpp
exllamav2/exllamav2_ext/ext_cache.cpp
exllamav2/exllamav2_ext/ext_cache.h
exllamav2/exllamav2_ext/ext_element.cpp
exllamav2/exllamav2_ext/ext_element.h
exllamav2/exllamav2_ext/ext_gemm.cpp
exllamav2/exllamav2_ext/ext_gemm.h
exllamav2/exllamav2_ext/ext_hadamard.cpp
exllamav2/exllamav2_ext/ext_hadamard.h
exllamav2/exllamav2_ext/ext_norm.cpp
exllamav2/exllamav2_ext/ext_norm.h
exllamav2/exllamav2_ext/ext_qattn.cpp
exllamav2/exllamav2_ext/ext_qattn.h
exllamav2/exllamav2_ext/ext_qmatrix.cpp
exllamav2/exllamav2_ext/ext_qmatrix.h
exllamav2/exllamav2_ext/ext_qmlp.cpp
exllamav2/exllamav2_ext/ext_qmlp.h
exllamav2/exllamav2_ext/ext_quant.cpp
exllamav2/exllamav2_ext/ext_quant.h
exllamav2-0.3.2.dist-info/LICENSE
exllamav2-0.3.2.dist-info/METADATA
exllamav2-0.3.2.dist-info/WHEEL
exllamav2-0.3.2.dist-info/top_level.txt
exllamav2-0.3.2.dist-info/RECORD
